vicsek/__init__.py
vicsek/lyapunov/__init__.py
vicsek/lyapunov/kernelized_vicsek.py
vicsek/models/__init__.py
vicsek/models/heterogeneous.py
vicsek/models/particle.py
vicsek/models/vicsek.py
vicsek/util/__init__.py
vicsek/util/cell_list.py
vicsek/util/factory.py
vicsek/util/linalg.py
pyvicsek-0.1.2.dist-info/LICENSE
pyvicsek-0.1.2.dist-info/METADATA
pyvicsek-0.1.2.dist-info/WHEEL
pyvicsek-0.1.2.dist-info/top_level.txt
pyvicsek-0.1.2.dist-info/RECORD
