Metadata-Version: 2.1
Name: pyvicsek
Version: 0.1.2
Author-email: Mehtan Rahman <mehtan.rahman@utexas.edu>
Maintainer-email: Mehtan Rahman <mehtan.rahman@utexas.edu>
License: MIT License
Project-URL: Repository, https://github.com/mehtan-rahman/PyVicsek`1   2 
Classifier: Programming Language :: Python
Requires-Python: >=3.10
License-File: LICENSE
Requires-Dist: numpy
Requires-Dist: matplotlib
Requires-Dist: tqdm
